{"file.group":"chris","city":"North Clarence","file.lastModifiedTime":"2025-01-12T11:24:48-0600","fragment.identifier":"2452bed6-c416-42a7-a00c-4dca173e1d21","fragment.index":"478","mime.type":"application/json","file.permissions":"rw-rw-r--","uuid":"7a07963b-3272-4a0a-b75b-150a1a5b77b6","absolute.path":"/home/chris/workspace/github.com/saxton-chris/DataEngineeringWithPython/output/","path":"/","filename":"Mason Waller","record.count":"1","name":"Mason Waller","file.creationTime":"2025-01-12T11:24:48-0600","file.lastAccessTime":"2025-01-12T11:25:39-0600","segment.original.filename":"data.json","file.owner":"chris","fragment.count":"1000","age":"70"}