{"file.group":"chris","city":"South Carlton","file.lastModifiedTime":"2025-01-12T11:24:48-0600","fragment.identifier":"2452bed6-c416-42a7-a00c-4dca173e1d21","fragment.index":"413","mime.type":"application/json","file.permissions":"rw-rw-r--","uuid":"d455cd82-e7bf-413b-96aa-1b678f481c2b","absolute.path":"/home/chris/workspace/github.com/saxton-chris/DataEngineeringWithPython/output/","path":"/","filename":"Darlene Robinson","record.count":"1","name":"Darlene Robinson","file.creationTime":"2025-01-12T11:24:48-0600","file.lastAccessTime":"2025-01-12T11:25:39-0600","segment.original.filename":"data.json","file.owner":"chris","fragment.count":"1000","age":"64"}